MANIFEST.in
setup.py
bin/mongoctl
mongoctl/__init__.py
mongoctl/binary_repo.py
mongoctl/config.py
mongoctl/errors.py
mongoctl/mongo_uri_tools.py
mongoctl/mongoctl.py
mongoctl/mongoctl_command_config.py
mongoctl/mongoctl_globals.py
mongoctl/mongoctl_logging.py
mongoctl/mongoctl_signal.py
mongoctl/mongodb_version.py
mongoctl/processes.py
mongoctl/prompt.py
mongoctl/repository.py
mongoctl/users.py
mongoctl/utils.py
mongoctl/version.py
mongoctl.egg-info/PKG-INFO
mongoctl.egg-info/SOURCES.txt
mongoctl.egg-info/dependency_links.txt
mongoctl.egg-info/pbr.json
mongoctl.egg-info/requires.txt
mongoctl.egg-info/top_level.txt
mongoctl/commands/__init__.py
mongoctl/commands/command_utils.py
mongoctl/commands/cluster/__init__.py
mongoctl/commands/cluster/configure.py
mongoctl/commands/cluster/list_clusters.py
mongoctl/commands/cluster/show.py
mongoctl/commands/common/__init__.py
mongoctl/commands/common/connect.py
mongoctl/commands/common/dump.py
mongoctl/commands/common/restore.py
mongoctl/commands/common/status.py
mongoctl/commands/misc/__init__.py
mongoctl/commands/misc/install.py
mongoctl/commands/misc/print_uri.py
mongoctl/commands/misc/publish_mongodb.py
mongoctl/commands/server/__init__.py
mongoctl/commands/server/list_servers.py
mongoctl/commands/server/restart.py
mongoctl/commands/server/resync_secondary.py
mongoctl/commands/server/show.py
mongoctl/commands/server/start.py
mongoctl/commands/server/stop.py
mongoctl/commands/server/tail_log.py
mongoctl/commands/sharding/__init__.py
mongoctl/commands/sharding/sharding.py
mongoctl/minify_json/__init__.py
mongoctl/minify_json/minify_json.py
mongoctl/objects/__init__.py
mongoctl/objects/base.py
mongoctl/objects/cluster.py
mongoctl/objects/mongod.py
mongoctl/objects/mongos.py
mongoctl/objects/replicaset_cluster.py
mongoctl/objects/server.py
mongoctl/objects/sharded_cluster.py
mongoctl/sample_conf/__init__.py
mongoctl/sample_conf/clusters.config
mongoctl/sample_conf/mongoctl.config
mongoctl/sample_conf/servers.config
mongoctl/tests/__init__.py
mongoctl/tests/auth_replicaset_test.py
mongoctl/tests/basic_test.py
mongoctl/tests/cmdline_servers_test.py
mongoctl/tests/install_test.py
