Metadata-Version: 1.0
Name: mongoctl
Version: 0.9.0
Summary: MongoDB command line utility
Home-page: https://github.com/mongolab/mongoctl
Author: MongoLab team
Author-email: team@mongolab.com
License: MIT
Platform: UNKNOWN
